{
    "$schema": "https://schema.management.azure.com/schemas/2018-05-01/subscriptionDeploymentParameters.json#",
    "contentVersion": "1.0.0.0",
    "parameters": {
        "mspOfferName": {
            "value": "Valto CSP Standard Support"
        },
        "mspOfferDescription": {
            "value": "Valto CSP Standard Support"
        },
        "managedByTenantId": {
            "value": "39721957-6032-4366-89c5-d6ac572beea3"
        },
        "authorizations": {
            "value": [
                { 
                    "principalId": "5527cd3b-91b6-4891-a1d6-e7fab9a1bb37", 
                    "roleDefinitionId": "b24988ac-6180-42a0-ab88-20f7382dd24c",
                    "principalIdDisplayName": "Valto Support - Contributor" 
                }, 

                { 
                    "principalId": "b525224a-7540-45eb-8321-d03c01d84e0c", 
                    "roleDefinitionId": "acdd72a7-3385-48ef-bd42-f606fba81ae7",
                    "principalIdDisplayName": "Valto Support - Reader" 
                }   
                
                
                    ]
                }                
        }
}